odoo10_addon_purchase_order_import-10.0.2.0.0-nspkg.pth
odoo/addons/purchase_order_import/README.rst
odoo/addons/purchase_order_import/__init__.py
odoo/addons/purchase_order_import/__manifest__.py
odoo/addons/purchase_order_import/i18n/es.po
odoo/addons/purchase_order_import/i18n/fr.po
odoo/addons/purchase_order_import/i18n/purchase_order_import.pot
odoo/addons/purchase_order_import/models/__init__.py
odoo/addons/purchase_order_import/models/purchase_order.py
odoo/addons/purchase_order_import/static/description/icon.png
odoo/addons/purchase_order_import/tests/__init__.py
odoo/addons/purchase_order_import/tests/test_order_response_import.py
odoo/addons/purchase_order_import/views/purchase.xml
odoo/addons/purchase_order_import/wizard/__init__.py
odoo/addons/purchase_order_import/wizard/order_response_import.py
odoo/addons/purchase_order_import/wizard/order_response_import_view.xml
odoo/addons/purchase_order_import/wizard/purchase_order_import.py
odoo/addons/purchase_order_import/wizard/purchase_order_import_view.xml
odoo10_addon_purchase_order_import-10.0.2.0.0.dist-info/METADATA
odoo10_addon_purchase_order_import-10.0.2.0.0.dist-info/WHEEL
odoo10_addon_purchase_order_import-10.0.2.0.0.dist-info/namespace_packages.txt
odoo10_addon_purchase_order_import-10.0.2.0.0.dist-info/top_level.txt
odoo10_addon_purchase_order_import-10.0.2.0.0.dist-info/RECORD
