Metadata-Version: 2.1
Name: odoo10-addon-purchase-order-import
Version: 10.0.2.0.0
Summary: Update RFQ via the import of quotations from suppliers
Home-page: http://www.akretion.com
Author: Akretion,Odoo Community Association (OCA)
Author-email: support@odoo-community.org
License: AGPL-3
Platform: UNKNOWN
Classifier: Programming Language :: Python
Classifier: Framework :: Odoo
Classifier: License :: OSI Approved :: GNU Affero General Public License v3
Requires-Python: ~=2.7
Requires-Dist: odoo10-addon-base-business-document-import-stock
Requires-Dist: odoo10-addon-onchange-helper
Requires-Dist: odoo (<10.1dev,>=10.0)
